django_saml2_auth/__init__.py
django_saml2_auth/conf.py
django_saml2_auth/urls.py
django_saml2_auth/utils.py
django_saml2_auth/views.py
django_saml2_auth/templates/django_saml2_auth/denied.html
django_saml2_auth/templates/django_saml2_auth/signout.html
django_saml2_auth_plus-1.0.0.dist-info/DESCRIPTION.rst
django_saml2_auth_plus-1.0.0.dist-info/METADATA
django_saml2_auth_plus-1.0.0.dist-info/RECORD
django_saml2_auth_plus-1.0.0.dist-info/WHEEL
django_saml2_auth_plus-1.0.0.dist-info/metadata.json
django_saml2_auth_plus-1.0.0.dist-info/top_level.txt
