Metadata-Version: 2.0
Name: django-saml2-auth-plus
Version: 1.0.0
Summary: Simple and Configurable Django SAML2 Authentication. Easily integrate with SAML2 SSO identity providers like Okta
Home-page: https://github.com/kronion/django-saml2-auth
Author: Collin Stedman
Author-email: zkronion+djsaml@gmail.com
License: Apache 2.0
Keywords: Simple Configurable Django SAML2 SSO Authentication Plus
Platform: UNKNOWN
Classifier: Development Status :: 5 - Production/Stable
Classifier: Intended Audience :: Developers
Classifier: Topic :: Software Development :: Libraries :: Python Modules
Classifier: License :: OSI Approved :: Apache Software License
Classifier: Framework :: Django :: 1.5
Classifier: Framework :: Django :: 1.6
Classifier: Framework :: Django :: 1.7
Classifier: Framework :: Django :: 1.8
Classifier: Framework :: Django :: 1.9
Classifier: Framework :: Django :: 1.10
Classifier: Framework :: Django :: 1.11
Classifier: Programming Language :: Python :: 2
Classifier: Programming Language :: Python :: 2.6
Classifier: Programming Language :: Python :: 2.7
Classifier: Programming Language :: Python :: 3
Classifier: Programming Language :: Python :: 3.3
Classifier: Programming Language :: Python :: 3.4
Classifier: Programming Language :: Python :: 3.5
Classifier: Programming Language :: Python :: 3.6
Requires-Dist: pysaml2 (==4.5.0)
